cbpro/__init__.py
cbpro/authenticated_client.py
cbpro/cbpro_auth.py
cbpro/order_book.py
cbpro/public_client.py
cbpro/websocket_client.py
cbpro_notbroken-1.1.5.dist-info/LICENSE
cbpro_notbroken-1.1.5.dist-info/METADATA
cbpro_notbroken-1.1.5.dist-info/WHEEL
cbpro_notbroken-1.1.5.dist-info/top_level.txt
cbpro_notbroken-1.1.5.dist-info/RECORD
